pyltk/__init__.py
pyltk/constants.py
pyltk/stemmer.py
pyltk/tokenizer.py
pyltk-0.0.2.dist-info/LICENSE
pyltk-0.0.2.dist-info/WHEEL
pyltk-0.0.2.dist-info/METADATA
pyltk-0.0.2.dist-info/RECORD
