Metadata-Version: 2.1
Name: pyltk
Version: 0.0.2
Summary: english tokenizer and stemmer
License: MIT
Author: wayfaring-stranger
Author-email: zw6p226m@duck.com
Requires-Python: >=3.8,<4.0
Classifier: License :: OSI Approved :: MIT License
Classifier: Programming Language :: Python :: 3
Classifier: Programming Language :: Python :: 3.8
Classifier: Programming Language :: Python :: 3.9
Classifier: Programming Language :: Python :: 3.10
